LICENSE
README.md
pyproject.toml
setup.cfg
setup.py
hdsr_pygithub/__init__.py
hdsr_pygithub/constants.py
hdsr_pygithub/exceptions.py
hdsr_pygithub.egg-info/PKG-INFO
hdsr_pygithub.egg-info/SOURCES.txt
hdsr_pygithub.egg-info/dependency_links.txt
hdsr_pygithub.egg-info/not-zip-safe
hdsr_pygithub.egg-info/requires.txt
hdsr_pygithub.egg-info/top_level.txt
hdsr_pygithub/downloader/__init__.py
hdsr_pygithub/downloader/base.py
hdsr_pygithub/downloader/dir.py
hdsr_pygithub/downloader/file.py
hdsr_pygithub/tests/__init__.py
hdsr_pygithub/tests/test_dir_downloader.py
hdsr_pygithub/tests/test_file_downloader.py
hdsr_pygithub/tests/test_general.py
hdsr_pygithub/tests/utils.py