Metadata-Version: 2.1
Name: hdsr-pygithub
Version: 1.10
Summary: An interface for interacting with hdsr github repos
Home-page: https://github.com/hdsr-mid/hdsr_pygithub
Download-URL: https://github.com/hdsr-mid/hdsr_pygithub/archive/v1.10.tar.gz
Author: Renier Kramer
Author-email: renier.kramer@hdsr.nl
License: MIT
Keywords: interface,interaction,github,files,hdsr
Classifier: Development Status :: 5 - Production/Stable
Classifier: Intended Audience :: Developers
Classifier: Topic :: Software Development :: Build Tools
Classifier: License :: OSI Approved :: MIT License
Classifier: Programming Language :: Python :: 3.7
Classifier: Programming Language :: Python :: 3.8
Classifier: Programming Language :: Python :: 3.9
Provides-Extra: test
License-File: LICENSE
